dated_money/__init__.py
dated_money/currency.py
dated_money/db_serialization.py
dated_money/logger.py
dated_money/money.py
dated_money/rates.py
dated_money-2.1.0.dist-info/METADATA
dated_money-2.1.0.dist-info/WHEEL
dated_money-2.1.0.dist-info/entry_points.txt
dated_money-2.1.0.dist-info/licenses/LICENSE
dated_money-2.1.0.dist-info/RECORD
