Metadata-Version: 2.4
Name: dated-money
Version: 2.1.0
Summary: Compute with dated monetary values.
Project-URL: Homepage, https://juanreyero.com/open/dated-money/
Project-URL: Repository, https://github.com/juanre/dated-money
Author-email: Juan Reyero <juan@juanreyero.com>
License: MIT
License-File: LICENSE
Requires-Python: >=3.9
Requires-Dist: python-dateutil>=2.9.0.post0
Requires-Dist: python-dotenv>=1.0.1
Requires-Dist: requests>=2.31.0
Requires-Dist: supabase>=2.11.0
